cashare/__init__.py
cashare/balance.py
cashare/cash_flow.py
cashare/daily.py
cashare/daily_2.py
cashare/econ.py
cashare/income.py
cashare/mc_data.py
cashare/minute_data.py
cashare/stock_div.py
cashare/stock_l.py
cashare/stock_now.py
cashare/stock_sp.py
cashare/ti_data.py
cashare/common/__init__.py
cashare/common/ad.py
cashare/common/c_now_get_data.py
cashare/common/dname.py
cashare/common/example.py
cashare/common/get_com.py
cashare/common/get_data.py
cashare/common/raise_mess.py
cashare/common/var_date.py
cashare/common/var_token.py
cashare/index/__init__.py
cashare/index/us_index_daily.py
cashare/index/us_index_member.py
cashare/index/us_industry.py
cashare/stock/__init__.py
cashare/stock/c_data.py
cashare/stock/c_min.py
cashare/stock/c_now.py
cashare-0.3.2.dist-info/LICENSE
cashare-0.3.2.dist-info/METADATA
cashare-0.3.2.dist-info/WHEEL
cashare-0.3.2.dist-info/top_level.txt
cashare-0.3.2.dist-info/RECORD
