Metadata-Version: 2.2
Name: cashare
Version: 0.3.2
Author: libai
Author-email: lbai45934@gmail.com
License: MIT License
Platform: any
License-File: LICENSE
Requires-Dist: httpx
Requires-Dist: datetime
Requires-Dist: pandas
Requires-Dist: tenacity
Dynamic: author
Dynamic: author-email
Dynamic: license
Dynamic: platform
Dynamic: requires-dist
